AUTHORS.rst
CONTRIBUTING.rst
HISTORY.rst
LICENSE
MANIFEST.in
README.rst
setup.cfg
setup.py
djangocms_instagram/__init__.py
djangocms_instagram/cms_plugins.py
djangocms_instagram/conf.py
djangocms_instagram/forms.py
djangocms_instagram/models.py
djangocms_instagram/widgets.py
djangocms_instagram.egg-info/PKG-INFO
djangocms_instagram.egg-info/SOURCES.txt
djangocms_instagram.egg-info/dependency_links.txt
djangocms_instagram.egg-info/not-zip-safe
djangocms_instagram.egg-info/pbr.json
djangocms_instagram.egg-info/requires.txt
djangocms_instagram.egg-info/top_level.txt
djangocms_instagram/migrations/0001_initial.py
djangocms_instagram/migrations/__init__.py
djangocms_instagram/south_migrations/0001_initial.py
djangocms_instagram/south_migrations/__init__.py
djangocms_instagram/static/admin/css/djangocms_instagram/djangocms_instagram.css
djangocms_instagram/static/admin/img/djangocms_instagram/icon_searchbox.png
djangocms_instagram/static/admin/img/djangocms_instagram/instagram_icon.png
djangocms_instagram/static/admin/js/djangocms_instagram/djangocms_instagram.js
djangocms_instagram/static/admin/js/djangocms_instagram/jquery.geocomplete.js
djangocms_instagram/static/admin/js/djangocms_instagram/jquery.init.js
djangocms_instagram/static/admin/js/djangocms_instagram/search.autocomplete.js
djangocms_instagram/static/css/djangocms_instagram/djangocms_instagram.css
djangocms_instagram/static/js/djangocms_instagram/djangocms_instagram.js
djangocms_instagram/templates/admin/djangocms_instagram/search.html
djangocms_instagram/templates/djangocms_instagram/default.html