Metadata-Version: 1.1
Name: djangocms-instagram
Version: 0.1.1
Summary: A simple but versatile Instagram plugin for your django-cms powered sites.
Home-page: https://github.com/mishbahr/djangocms-instagram
Author: Mishbah Razzaque
Author-email: mishbahx@gmail.com
License: BSD
Keywords: djangocms-instagram
Platform: UNKNOWN
Classifier: Development Status :: 4 - Beta
Classifier: Framework :: Django
Classifier: Intended Audience :: Developers
Classifier: License :: OSI Approved :: BSD License
Classifier: Natural Language :: English
Classifier: Programming Language :: Python :: 2
Classifier: Programming Language :: Python :: 2.6
Classifier: Programming Language :: Python :: 2.7
Classifier: Programming Language :: Python :: 3
Classifier: Programming Language :: Python :: 3.3
